{
  "title": "తెలుగు తోట - 1",
  "subtitle": "ఎనవ తరగతి",
  "lines": [
    {
      "words": [
        {
          "telugu": "పాఠ్యపుస్తక",
          "english": "Textbook"
        },
        {
          "telugu": "అభివృద్ధి,",
          "english": "Development,"
        },
        {
          "telugu": "ప్రచురణ",
          "english": "Publication"
        },
        {
          "telugu": "సమితి",
          "english": "Committee"
        }
      ]
    },
    {
      "words": [
        {
          "telugu": "శ్రీ",
          "english": "Sri"
        },
        {
          "telugu": "ప్రదీప్",
          "english": "Pradeep"
        },
        {
          "telugu": "కుమార్",
          "english": "Kumar"
        },
        {
          "telugu": "I.A.S",
          "english": "I.A.S"
        },
        {
          "telugu": "శ్రీ",
          "english": "Sri"
        },
        {
          "telugu": "ఎన్.",
          "english": "N."
        },
        {
          "telugu": "సురేష్",
          "english": "Suresh"
        },
        {
          "telugu": "కుమార్",
          "english": "Kumar"
        },
        {
          "telugu": "I.A.S",
          "english": "I.A.S"
        }
      ]
    },
    {
      "words": [
        {
          "telugu": "ప్రభుత్వ",
          "english": "Government"
        },
        {
          "telugu": "ప్రధాన",
          "english": "Chief"
        },
        {
          "telugu": "కార్యదర్శి,",
          "english": "Secretary,"
        },
        {
          "telugu": "పాఠశాల",
          "english": "School"
        },
        {
          "telugu": "విద్య,",
          "english": "Education,"
        },
        {
          "telugu": "ఆంధ్రప్రదేశ్",
          "english": "Andhra Pradesh"
        },
        {
          "telugu": "కమిషనర్,",
          "english": "Commissioner,"
        },
        {
          "telugu": "పాఠశాల",
          "english": "School"
        },
        {
          "telugu": "విద్య,",
          "english": "Education,"
        },
        {
          "telugu": "ఆంధ్రప్రదేశ్",
          "english": "Andhra Pradesh"
        }
      ]
    },
    {
      "words": [
        {
          "telugu": "శ్రీ",
          "english": "Sri"
        },
        {
          "telugu": "జి.",
          "english": "G."
        },
        {
          "telugu": "చిన్నారావు",
          "english": "Chinnarao"
        },
        {
          "telugu": "I.A.S",
          "english": "I.A.S"
        },
        {
          "telugu": "శ్రీ",
          "english": "Sri"
        },
        {
          "telugu": "కె.",
          "english": "K."
        },
        {
          "telugu": "రవీంద్రనాథ్",
          "english": "Ravindranath"
        },
        {
          "telugu": "రెడ్డి,",
          "english": "Reddy,"
        },
        {
          "telugu": "M.A.,",
          "english": "M.A.,"
        },
        {
          "telugu": "B.Ed.,",
          "english": "B.Ed.,"
        }
      ]
    },
    {
      "words": [
        {
          "telugu": "స్పెషల్",
          "english": "Special"
        },
        {
          "telugu": "ప్రోజెక్ట్",
          "english": "Project"
        },
        {
          "telugu": "డైరెక్టర్,",
          "english": "Director,"
        },
        {
          "telugu": "సమగ్ర",
          "english": "Integrated"
        },
        {
          "telugu": "శిక్ష,",
          "english": "Shiksha,"
        },
        {
          "telugu": "ఆంధ్రప్రదేశ్",
          "english": "Andhra Pradesh"
        },
        {
          "telugu": "సంచాలకులు,",
          "english": "Director,"
        },
        {
          "telugu": "ప్రభుత్వ",
          "english": "Government"
        },
        {
          "telugu": "పాఠ్యపుస్తక",
          "english": "Textbook"
        },
        {
          "telugu": "ముద్రణాలయం,",
          "english": "Press,"
        },
        {
          "telugu": "ఆంధ్రప్రదేశ్",
          "english": "Andhra Pradesh"
        }
      ]
    },
    {
      "words": [
        {
          "telugu": "డా॥",
          "english": "Dr."
        },
        {
          "telugu": "డి.",
          "english": "D."
        },
        {
          "telugu": "ప్రతాప్",
          "english": "Pratap"
        },
        {
          "telugu": "రెడ్డి",
          "english": "Reddy"
        },
        {
          "telugu": "M.A.,",
          "english": "M.A.,"
        },
        {
          "telugu": "B.Ed.,",
          "english": "B.Ed.,"
        },
        {
          "telugu": "Ph.D",
          "english": "Ph.D"
        }
      ]
    },
    {
      "words": [
        {
          "telugu": "సంచాలకులు,",
          "english": "Director,"
        },
        {
          "telugu": "రాష్ట్ర",
          "english": "State"
        },
        {
          "telugu": "విద్యా",
          "english": "Educational"
        },
        {
          "telugu": "పరిశోధనా",
          "english": "Research"
        },
        {
          "telugu": "శిక్షణా",
          "english": "Training"
        },
        {
          "telugu": "సంస్థ,",
          "english": "Institute,"
        },
        {
          "telugu": "ఆంధ్రప్రదేశ్",
          "english": "Andhra Pradesh"
        }
      ]
    },
    {
      "words": [
        {
          "telugu": "కార్యక్రమ",
          "english": "Program"
        },
        {
          "telugu": "సమన్వయకర్త",
          "english": "Coordinator"
        }
      ]
    },
    {
      "words": [
        {
          "telugu": "డా॥",
          "english": "Dr."
        },
        {
          "telugu": "జి.",
          "english": "G."
        },
        {
          "telugu": "కేశవ",
          "english": "Keshav"
        },
        {
          "telugu": "రెడ్డి",
          "english": "Reddy"
        },
        {
          "telugu": "M.Sc.,",
          "english": "M.Sc.,"
        },
        {
          "telugu": "M.Sc.,",
          "english": "M.Sc.,"
        },
        {
          "telugu": "M.Ed.,",
          "english": "M.Ed.,"
        },
        {
          "telugu": "M.Phil.,",
          "english": "M.Phil.,"
        },
        {
          "telugu": "Ph.D",
          "english": "Ph.D"
        }
      ]
    },
    {
      "words": [
        {
          "telugu": "ఆచార్యులు,",
          "english": "Professor,"
        },
        {
          "telugu": "విద్యాప్రణాళిక",
          "english": "Curriculum"
        },
        {
          "telugu": "పాఠ్యపుస్తక",
          "english": "Textbook"
        },
        {
          "telugu": "విభాగము,",
          "english": "Department,"
        },
        {
          "telugu": "రాష్ట్ర",
          "english": "State"
        },
        {
          "telugu": "విద్యాపరిశోధనా",
          "english": "Educational Research"
        },
        {
          "telugu": "శిక్షణా",
          "english": "Training"
        },
        {
          "telugu": "సంస్థ,",
          "english": "Institute,"
        },
        {
          "telugu": "ఆంధ్రప్రదేశ్",
          "english": "Andhra Pradesh"
        }
      ]
    },
    {
      "words": [
        {
          "telugu": "సంపాదక",
          "english": "Editorial"
        },
        {
          "telugu": "వర్గం",
          "english": "Board"
        }
      ]
    },
    {
      "words": [
        {
          "telugu": "డా.",
          "english": "Dr."
        },
        {
          "telugu": "డి.",
          "english": "D."
        },
        {
          "telugu": "చంద్రశేఖరరెడ్డి",
          "english": "Chandrashekar Reddy"
        }
      ]
    },
    {
      "words": [
        {
          "telugu": "విశ్రాంత",
          "english": "Retired"
        },
        {
          "telugu": "ప్రధానాచార్యులు,",
          "english": "Principal,"
        },
        {
          "telugu": "ఆంధ్ర",
          "english": "Andhra"
        },
        {
          "telugu": "సారస్వత",
          "english": "Literary"
        },
        {
          "telugu": "పరిషత్",
          "english": "Council"
        },
        {
          "telugu": "ప్రాచ్యకళాశాల,",
          "english": "Oriental College,"
        },
        {
          "telugu": "హైదరాబాద్.",
          "english": "Hyderabad."
        }
      ]
    },
    {
      "words": [
        {
          "telugu": "డా.",
          "english": "Dr."
        },
        {
          "telugu": "రామమోహన్",
          "english": "Ramamohan"
        },
        {
          "telugu": "చంద్రశేఖరరెడ్డి",
          "english": "Chandrashekar Reddy"
        }
      ]
    },
    {
      "words": [
        {
          "telugu": "విశ్రాంత",
          "english": "Retired"
        },
        {
          "telugu": "ఆచార్యులు,",
          "english": "Professor,"
        },
        {
          "telugu": "శ్రీ",
          "english": "Sri"
        },
        {
          "telugu": "కృష్ణదేవరాయ",
          "english": "Krishnadevaraya"
        },
        {
          "telugu": "విశ్వవిద్యాలయం,",
          "english": "University,"
        },
        {
          "telugu": "అనంతపురం,",
          "english": "Anantapur,"
        }
      ]
    },
    {
      "words": [
        {
          "telugu": "డా.",
          "english": "Dr."
        },
        {
          "telugu": "వరివి",
          "english": "Varivi"
        },
        {
          "telugu": "రామకృష్ణారావు",
          "english": "Ramakrishna Rao"
        }
      ]
    },
    {
      "words": [
        {
          "telugu": "విశ్రాంత",
          "english": "Retired"
        },
        {
          "telugu": "తెలుగు",
          "english": "Telugu"
        },
        {
          "telugu": "ఆచార్యులు,",
          "english": "Professor,"
        },
        {
          "telugu": "కేంద్ర",
          "english": "Central"
        },
        {
          "telugu": "విశ్వవిద్యాలయం,",
          "english": "University,"
        },
        {
          "telugu": "హైదరాబాద్.",
          "english": "Hyderabad."
        }
      ]
    },
    {
      "words": [
        {
          "telugu": "డా.",
          "english": "Dr."
        },
        {
          "telugu": "కదివెళ్ళ",
          "english": "Kadivella"
        },
        {
          "telugu": "శర్మ",
          "english": "Sharma"
        },
        {
          "telugu": "ప్రసాద్",
          "english": "Prasad"
        }
      ]
    },
    {
      "words": [
        {
          "telugu": "విశ్రాంత",
          "english": "Retired"
        },
        {
          "telugu": "తెలుగు",
          "english": "Telugu"
        },
        {
          "telugu": "పండితులు,",
          "english": "Scholars,"
        },
        {
          "telugu": "సూర్యాపేట,",
          "english": "Suryapet,"
        },
        {
          "telugu": "పశ్చిమగోదావరి.",
          "english": "West Godavari."
        }
      ]
    },
    {
      "words": [
        {
          "telugu": "శ్రీ",
          "english": "Sri"
        },
        {
          "telugu": "అలూరు",
          "english": "Aluru"
        },
        {
          "telugu": "వేంకటేశ్వరమ్మ",
          "english": "Venkateshwaramma"
        }
      ]
    },
    {
      "words": [
        {
          "telugu": "విశ్రాంత",
          "english": "Retired"
        },
        {
          "telugu": "తెలుగు",
          "english": "Telugu"
        },
        {
          "telugu": "పండితులు,",
          "english": "Scholars,"
        },
        {
          "telugu": "నెల్లూరు",
          "english": "Nellore"
        }
      ]
    },
    {
      "words": [
        {
          "telugu": "గౌరవ",
          "english": "Honorary"
        },
        {
          "telugu": "సంపాదకులు",
          "english": "Editors"
        }
      ]
    },
    {
      "words": [
        {
          "telugu": "శ్రీ",
          "english": "Sri"
        },
        {
          "telugu": "వాడ్రేవు",
          "english": "Vadrevu"
        },
        {
          "telugu": "చంద్రశేఖరరావు",
          "english": "Chandrashekhara Rao"
        }
      ]
    },
    {
      "words": [
        {
          "telugu": "విశ్రాంత",
          "english": "Retired"
        },
        {
          "telugu": "అధ్యాపకులు,",
          "english": "Lecturers,"
        },
        {
          "telugu": "కముక్",
          "english": "Kamuk"
        }
      ]
    },
    {
      "words": [
        {
          "telugu": "డా.",
          "english": "Dr."
        },
        {
          "telugu": "సి.వి.",
          "english": "C.V."
        },
        {
          "telugu": "ప్రసాద్",
          "english": "Prasad"
        },
        {
          "telugu": "నాయకత్వ",
          "english": "Leadership"
        },
        {
          "telugu": "జాతీయ",
          "english": "National"
        },
        {
          "telugu": "సమితి",
          "english": "Committee"
        },
        {
          "telugu": "సభ్యులు",
          "english": "Members"
        }
      ]
    },
    {
      "words": [
        {
          "telugu": "శ్రీ",
          "english": "Sri"
        },
        {
          "telugu": "సి.వి.",
          "english": "C.V."
        },
        {
          "telugu": "కృష్ణయ్య",
          "english": "Krishnaiah"
        }
      ]
    },
    {
      "words": [
        {
          "telugu": "విశ్రాంత",
          "english": "Retired"
        },
        {
          "telugu": "ఉపాధ్యాయులు,",
          "english": "Teachers,"
        },
        {
          "telugu": "స్టేట్",
          "english": "State"
        },
        {
          "telugu": "ఎస్",
          "english": "S"
        }
      ]
    },
    {
      "words": [
        {
          "telugu": "సమగ్ర",
          "english": "Integrated"
        },
        {
          "telugu": "శిక్ష,",
          "english": "Shiksha,"
        },
        {
          "telugu": "ఆంధ్రప్రదేశ్",
          "english": "Andhra Pradesh"
        },
        {
          "telugu": "ప్రభుత్వం",
          "english": "Government"
        },
        {
          "telugu": "వారిచేత",
          "english": "by them"
        },
        {
          "telugu": "ముద్రించబడింది",
          "english": "was printed"
        }
      ]
    }
  ],
  "pageType": "info",
  "hasExercise": false,
  "exerciseType": null,
  "illustrationArea": null
}